[
  {
    "step": 100,
    "elapsed_s": 720,
    "val_psnr": 30.0,
    "val_lpips": 0.0339
  },
  {
    "step": 200,
    "elapsed_s": 1246,
    "val_psnr": 30.13,
    "val_lpips": 0.0308
  },
  {
    "step": 300,
    "elapsed_s": 1770,
    "val_psnr": 30.2,
    "val_lpips": 0.0294
  },
  {
    "step": 400,
    "elapsed_s": 2294,
    "val_psnr": 30.24,
    "val_lpips": 0.0286
  },
  {
    "step": 500,
    "elapsed_s": 2815,
    "val_psnr": 30.28,
    "val_lpips": 0.0281
  },
  {
    "step": 600,
    "elapsed_s": 3338,
    "val_psnr": 30.24,
    "val_lpips": 0.0278
  },
  {
    "step": 700,
    "elapsed_s": 3859,
    "val_psnr": 30.26,
    "val_lpips": 0.0277
  },
  {
    "step": 800,
    "elapsed_s": 4380,
    "val_psnr": 30.29,
    "val_lpips": 0.0274
  },
  {
    "step": 900,
    "elapsed_s": 4901,
    "val_psnr": 30.28,
    "val_lpips": 0.0272
  },
  {
    "step": 1000,
    "elapsed_s": 5423,
    "val_psnr": 30.29,
    "val_lpips": 0.027
  },
  {
    "step": 1100,
    "elapsed_s": 5944,
    "val_psnr": 30.28,
    "val_lpips": 0.0269
  },
  {
    "step": 1200,
    "elapsed_s": 6465,
    "val_psnr": 30.28,
    "val_lpips": 0.0268
  },
  {
    "step": 1300,
    "elapsed_s": 6983,
    "val_psnr": 30.29,
    "val_lpips": 0.0267
  },
  {
    "step": 1400,
    "elapsed_s": 7500,
    "val_psnr": 30.31,
    "val_lpips": 0.0264
  },
  {
    "step": 1500,
    "elapsed_s": 8017,
    "val_psnr": 30.27,
    "val_lpips": 0.0265
  },
  {
    "step": 1600,
    "elapsed_s": 8534,
    "val_psnr": 30.33,
    "val_lpips": 0.0263
  },
  {
    "step": 1700,
    "elapsed_s": 9050,
    "val_psnr": 30.3,
    "val_lpips": 0.0262
  },
  {
    "step": 1800,
    "elapsed_s": 9568,
    "val_psnr": 30.33,
    "val_lpips": 0.0261
  },
  {
    "step": 1900,
    "elapsed_s": 10087,
    "val_psnr": 30.32,
    "val_lpips": 0.0263
  },
  {
    "step": 2000,
    "elapsed_s": 10604,
    "val_psnr": 30.33,
    "val_lpips": 0.026
  },
  {
    "step": 2100,
    "elapsed_s": 11123,
    "val_psnr": 30.31,
    "val_lpips": 0.0259
  },
  {
    "step": 2200,
    "elapsed_s": 11642,
    "val_psnr": 30.32,
    "val_lpips": 0.0259
  },
  {
    "step": 2300,
    "elapsed_s": 12159,
    "val_psnr": 30.33,
    "val_lpips": 0.0259
  },
  {
    "step": 2400,
    "elapsed_s": 12677,
    "val_psnr": 30.34,
    "val_lpips": 0.0258
  },
  {
    "step": 2500,
    "elapsed_s": 13194,
    "val_psnr": 30.36,
    "val_lpips": 0.0256
  },
  {
    "step": 2600,
    "elapsed_s": 13710,
    "val_psnr": 30.34,
    "val_lpips": 0.0255
  },
  {
    "step": 2700,
    "elapsed_s": 14225,
    "val_psnr": 30.38,
    "val_lpips": 0.0258
  },
  {
    "step": 2800,
    "elapsed_s": 14741,
    "val_psnr": 30.36,
    "val_lpips": 0.0254
  },
  {
    "step": 2900,
    "elapsed_s": 15255,
    "val_psnr": 30.4,
    "val_lpips": 0.0252
  },
  {
    "step": 3000,
    "elapsed_s": 15771,
    "val_psnr": 30.4,
    "val_lpips": 0.0251
  },
  {
    "step": 3100,
    "elapsed_s": 16289,
    "val_psnr": 30.36,
    "val_lpips": 0.0251
  },
  {
    "step": 3200,
    "elapsed_s": 16805,
    "val_psnr": 30.37,
    "val_lpips": 0.0252
  },
  {
    "step": 3300,
    "elapsed_s": 17323,
    "val_psnr": 30.38,
    "val_lpips": 0.0252
  },
  {
    "step": 3400,
    "elapsed_s": 17840,
    "val_psnr": 30.36,
    "val_lpips": 0.025
  },
  {
    "step": 3500,
    "elapsed_s": 18356,
    "val_psnr": 30.36,
    "val_lpips": 0.025
  },
  {
    "step": 3600,
    "elapsed_s": 18871,
    "val_psnr": 30.28,
    "val_lpips": 0.0251
  },
  {
    "step": 3700,
    "elapsed_s": 19387,
    "val_psnr": 30.41,
    "val_lpips": 0.0249
  },
  {
    "step": 3800,
    "elapsed_s": 19903,
    "val_psnr": 30.4,
    "val_lpips": 0.025
  },
  {
    "step": 3900,
    "elapsed_s": 20420,
    "val_psnr": 30.37,
    "val_lpips": 0.0248
  },
  {
    "step": 4000,
    "elapsed_s": 20938,
    "val_psnr": 30.42,
    "val_lpips": 0.0247
  },
  {
    "step": 4100,
    "elapsed_s": 21455,
    "val_psnr": 30.41,
    "val_lpips": 0.0246
  },
  {
    "step": 4200,
    "elapsed_s": 21971,
    "val_psnr": 30.42,
    "val_lpips": 0.0246
  },
  {
    "step": 4300,
    "elapsed_s": 22488,
    "val_psnr": 30.44,
    "val_lpips": 0.0246
  },
  {
    "step": 4400,
    "elapsed_s": 23003,
    "val_psnr": 30.4,
    "val_lpips": 0.0246
  },
  {
    "step": 4500,
    "elapsed_s": 23518,
    "val_psnr": 30.42,
    "val_lpips": 0.0247
  },
  {
    "step": 4600,
    "elapsed_s": 24034,
    "val_psnr": 30.39,
    "val_lpips": 0.0245
  },
  {
    "step": 4700,
    "elapsed_s": 24551,
    "val_psnr": 30.37,
    "val_lpips": 0.0248
  },
  {
    "step": 4800,
    "elapsed_s": 25068,
    "val_psnr": 30.42,
    "val_lpips": 0.0244
  },
  {
    "step": 4900,
    "elapsed_s": 25586,
    "val_psnr": 30.46,
    "val_lpips": 0.0243
  },
  {
    "step": 5000,
    "elapsed_s": 26103,
    "val_psnr": 30.41,
    "val_lpips": 0.0242
  },
  {
    "step": 5100,
    "elapsed_s": 26619,
    "val_psnr": 30.36,
    "val_lpips": 0.0243
  },
  {
    "step": 5200,
    "elapsed_s": 27134,
    "val_psnr": 30.41,
    "val_lpips": 0.0243
  },
  {
    "step": 5300,
    "elapsed_s": 27647,
    "val_psnr": 30.43,
    "val_lpips": 0.0244
  },
  {
    "step": 5400,
    "elapsed_s": 28162,
    "val_psnr": 30.43,
    "val_lpips": 0.0245
  },
  {
    "step": 5500,
    "elapsed_s": 28679,
    "val_psnr": 30.43,
    "val_lpips": 0.0244
  },
  {
    "step": 5600,
    "elapsed_s": 29194,
    "val_psnr": 30.42,
    "val_lpips": 0.0243
  },
  {
    "step": 5700,
    "elapsed_s": 29709,
    "val_psnr": 30.43,
    "val_lpips": 0.0245
  },
  {
    "step": 5800,
    "elapsed_s": 30224,
    "val_psnr": 30.43,
    "val_lpips": 0.0242
  },
  {
    "step": 5900,
    "elapsed_s": 30739,
    "val_psnr": 30.43,
    "val_lpips": 0.0242
  },
  {
    "step": 6000,
    "elapsed_s": 31253,
    "val_psnr": 30.38,
    "val_lpips": 0.0242
  },
  {
    "step": 6100,
    "elapsed_s": 31768,
    "val_psnr": 30.46,
    "val_lpips": 0.0241
  },
  {
    "step": 6200,
    "elapsed_s": 32282,
    "val_psnr": 30.36,
    "val_lpips": 0.0241
  },
  {
    "step": 6300,
    "elapsed_s": 32796,
    "val_psnr": 30.44,
    "val_lpips": 0.024
  },
  {
    "step": 6400,
    "elapsed_s": 33311,
    "val_psnr": 30.4,
    "val_lpips": 0.0241
  },
  {
    "step": 6500,
    "elapsed_s": 33824,
    "val_psnr": 30.39,
    "val_lpips": 0.024
  },
  {
    "step": 6600,
    "elapsed_s": 34338,
    "val_psnr": 30.34,
    "val_lpips": 0.0241
  },
  {
    "step": 6700,
    "elapsed_s": 34853,
    "val_psnr": 30.43,
    "val_lpips": 0.024
  },
  {
    "step": 6800,
    "elapsed_s": 35366,
    "val_psnr": 30.44,
    "val_lpips": 0.024
  },
  {
    "step": 6900,
    "elapsed_s": 35881,
    "val_psnr": 30.44,
    "val_lpips": 0.0238
  },
  {
    "step": 7000,
    "elapsed_s": 36396,
    "val_psnr": 30.44,
    "val_lpips": 0.0239
  },
  {
    "step": 7100,
    "elapsed_s": 36911,
    "val_psnr": 30.41,
    "val_lpips": 0.024
  },
  {
    "step": 7200,
    "elapsed_s": 37427,
    "val_psnr": 30.43,
    "val_lpips": 0.0238
  },
  {
    "step": 7300,
    "elapsed_s": 37945,
    "val_psnr": 30.51,
    "val_lpips": 0.0239
  },
  {
    "step": 7400,
    "elapsed_s": 38461,
    "val_psnr": 30.47,
    "val_lpips": 0.0239
  },
  {
    "step": 7500,
    "elapsed_s": 38979,
    "val_psnr": 30.45,
    "val_lpips": 0.0237
  },
  {
    "step": 7600,
    "elapsed_s": 39498,
    "val_psnr": 30.44,
    "val_lpips": 0.0237
  },
  {
    "step": 7700,
    "elapsed_s": 40015,
    "val_psnr": 30.43,
    "val_lpips": 0.0238
  },
  {
    "step": 7800,
    "elapsed_s": 40534,
    "val_psnr": 30.49,
    "val_lpips": 0.0235
  },
  {
    "step": 7900,
    "elapsed_s": 41053,
    "val_psnr": 30.38,
    "val_lpips": 0.0237
  },
  {
    "step": 8000,
    "elapsed_s": 41571,
    "val_psnr": 30.49,
    "val_lpips": 0.0236
  },
  {
    "step": 8100,
    "elapsed_s": 42089,
    "val_psnr": 30.35,
    "val_lpips": 0.0236
  },
  {
    "step": 8200,
    "elapsed_s": 42607,
    "val_psnr": 30.47,
    "val_lpips": 0.0235
  },
  {
    "step": 8300,
    "elapsed_s": 43122,
    "val_psnr": 30.45,
    "val_lpips": 0.0234
  },
  {
    "step": 8400,
    "elapsed_s": 43639,
    "val_psnr": 30.4,
    "val_lpips": 0.0235
  },
  {
    "step": 8500,
    "elapsed_s": 44157,
    "val_psnr": 30.44,
    "val_lpips": 0.0235
  },
  {
    "step": 8600,
    "elapsed_s": 44673,
    "val_psnr": 30.43,
    "val_lpips": 0.0235
  },
  {
    "step": 8700,
    "elapsed_s": 45191,
    "val_psnr": 30.48,
    "val_lpips": 0.0235
  },
  {
    "step": 8800,
    "elapsed_s": 45709,
    "val_psnr": 30.51,
    "val_lpips": 0.0234
  },
  {
    "step": 8900,
    "elapsed_s": 46226,
    "val_psnr": 30.44,
    "val_lpips": 0.0234
  },
  {
    "step": 9000,
    "elapsed_s": 46745,
    "val_psnr": 30.45,
    "val_lpips": 0.0234
  },
  {
    "step": 9100,
    "elapsed_s": 47264,
    "val_psnr": 30.45,
    "val_lpips": 0.0233
  },
  {
    "step": 9200,
    "elapsed_s": 47782,
    "val_psnr": 30.5,
    "val_lpips": 0.0233
  },
  {
    "step": 9300,
    "elapsed_s": 48300,
    "val_psnr": 30.52,
    "val_lpips": 0.0233
  },
  {
    "step": 9400,
    "elapsed_s": 48819,
    "val_psnr": 30.38,
    "val_lpips": 0.0234
  },
  {
    "step": 9500,
    "elapsed_s": 49338,
    "val_psnr": 30.5,
    "val_lpips": 0.0232
  },
  {
    "step": 9600,
    "elapsed_s": 49856,
    "val_psnr": 30.48,
    "val_lpips": 0.0233
  },
  {
    "step": 9700,
    "elapsed_s": 50375,
    "val_psnr": 30.54,
    "val_lpips": 0.0232
  },
  {
    "step": 9800,
    "elapsed_s": 50893,
    "val_psnr": 30.53,
    "val_lpips": 0.0231
  },
  {
    "step": 9900,
    "elapsed_s": 51412,
    "val_psnr": 30.53,
    "val_lpips": 0.0233
  },
  {
    "step": 10000,
    "elapsed_s": 51931,
    "val_psnr": 30.54,
    "val_lpips": 0.0231
  },
  {
    "step": 10100,
    "elapsed_s": 52449,
    "val_psnr": 30.46,
    "val_lpips": 0.0233
  },
  {
    "step": 10200,
    "elapsed_s": 52967,
    "val_psnr": 30.55,
    "val_lpips": 0.023
  },
  {
    "step": 10300,
    "elapsed_s": 53487,
    "val_psnr": 30.5,
    "val_lpips": 0.023
  },
  {
    "step": 10400,
    "elapsed_s": 54005,
    "val_psnr": 30.51,
    "val_lpips": 0.0231
  },
  {
    "step": 10500,
    "elapsed_s": 54524,
    "val_psnr": 30.52,
    "val_lpips": 0.0231
  },
  {
    "step": 10600,
    "elapsed_s": 55043,
    "val_psnr": 30.52,
    "val_lpips": 0.0229
  },
  {
    "step": 10700,
    "elapsed_s": 55561,
    "val_psnr": 30.45,
    "val_lpips": 0.0233
  }
]